<Properties StartupConfiguration="{1D47654B-FBDF-425D-CD58-885C2B09C17F}|">
  <MonoDevelop.Ide.Workbench ActiveDocument="Assets/Scripts/Spinner.cs">
    <Files>
      <File FileName="Assets/Scripts/Spinner.cs" Line="158" Column="7" />
    </Files>
    <Pads>
      <Pad Id="ProjectPad">
        <State name="__root__">
          <Node name="BonusWheel" expanded="True">
            <Node name="Assets" expanded="True">
              <Node name="Scripts" expanded="True">
                <Node name="Spinner.cs" selected="True" />
              </Node>
            </Node>
          </Node>
        </State>
      </Pad>
    </Pads>
  </MonoDevelop.Ide.Workbench>
  <MonoDevelop.Ide.DebuggingService.PinnedWatches />
  <MonoDevelop.Ide.Workspace ActiveConfiguration="Debug" />
  <MonoDevelop.Ide.ItemProperties.Assembly-CSharp PreferredExecutionTarget="221e2d1e-c62e-4675-8526-b925d803d637" />
  <MonoDevelop.Ide.DebuggingService.Breakpoints>
    <BreakpointStore />
  </MonoDevelop.Ide.DebuggingService.Breakpoints>
  <MultiItemStartupConfigurations />
</Properties>